{
        "intro":[
        {
            "name": "experiment_slides"
        },
        {
            "name": "experiment_slides1"
        },
        {
            "name": "experiment_slides2"
        },
        {
            "name": "experiment_slides3"
        },
        {
            "name": "experiment_slides4"
        },
        {
            "name": "experiment_slides5"
        },
        {
            "name": "experiment_slides6"
        },
        {
            "name": "experiment_slides7"
        },
        {
            "name": "experiment_slides8"
        },
        {
            "name": "experiment_slides9"
        },
        {
            "name": "experiment_slides10"
        },
        {
            "name": "experiment_slides11"
        },
        {
            "name": "experiment_slides12"
        },
        {
            "name": "experiment_slides13"
        }
    ],
        "stim":[
        {
            "name": "vidcap"
        },
        {
            "name": "vidcap2"
        }
    ],
    "text": "",
    "questions":[
        {"q": " ''How bad was what the Blue did to the Green?'' ", 
        "type": "caused",
        "l": ["not bad at all", "", "very bad"]}
    ]
}


 
